django_reversion_rest_framework-3.0.0.dist-info/licenses/LICENSE
reversion_rest_framework/__init__.py
reversion_rest_framework/mixins.py
reversion_rest_framework/serializers.py
reversion_rest_framework/viewsets.py
django_reversion_rest_framework-3.0.0.dist-info/METADATA
django_reversion_rest_framework-3.0.0.dist-info/WHEEL
django_reversion_rest_framework-3.0.0.dist-info/top_level.txt
django_reversion_rest_framework-3.0.0.dist-info/RECORD
