Metadata-Version: 2.4
Name: django-reversion-rest-framework
Version: 3.0.0
Summary: A package for adding a django-reversion history endpoint to django-rest-framework ModelViewSet
Home-page: https://github.com/dennybiasiolli/django-reversion-rest-framework
Author: Denny Biasiolli
Author-email: Denny Biasiolli <denny.biasiolli@gmail.com>
Project-URL: Homepage, https://github.com/dennybiasiolli/django-reversion-rest-framework
Project-URL: Bug Tracker, https://github.com/dennybiasiolli/django-reversion-rest-framework/issues
Classifier: Development Status :: 5 - Production/Stable
Classifier: Environment :: Web Environment
Classifier: Intended Audience :: Developers
Classifier: Programming Language :: Python :: 3
Classifier: License :: OSI Approved :: MIT License
Classifier: Operating System :: OS Independent
Classifier: Framework :: Django
Requires-Python: >=3.10
License-File: LICENSE
Requires-Dist: django-reversion>=4
Requires-Dist: djangorestframework>=3
Dynamic: license-file
